em6_api/__init__.py
em6_api/_modidx.py
em6_api/core.py
em6_api-0.0.4.dist-info/LICENSE
em6_api-0.0.4.dist-info/METADATA
em6_api-0.0.4.dist-info/WHEEL
em6_api-0.0.4.dist-info/entry_points.txt
em6_api-0.0.4.dist-info/top_level.txt
em6_api-0.0.4.dist-info/RECORD
